odoo/addons/connector_equipment_service/README.rst
odoo/addons/connector_equipment_service/__init__.py
odoo/addons/connector_equipment_service/__manifest__.py
odoo/addons/connector_equipment_service/i18n/connector_equipment_service.pot
odoo/addons/connector_equipment_service/models/__init__.py
odoo/addons/connector_equipment_service/models/agreement_serviceprofile.py
odoo/addons/connector_equipment_service/models/maintenance_equipment.py
odoo/addons/connector_equipment_service/readme/CONFIGURE.rst
odoo/addons/connector_equipment_service/readme/CONTRIBUTORS.rst
odoo/addons/connector_equipment_service/readme/DESCRIPTION.rst
odoo/addons/connector_equipment_service/readme/USAGE.rst
odoo/addons/connector_equipment_service/static/description/icon.png
odoo/addons/connector_equipment_service/static/description/index.html
odoo12_addon_connector_equipment_service-12.0.1.1.0.dist-info/METADATA
odoo12_addon_connector_equipment_service-12.0.1.1.0.dist-info/WHEEL
odoo12_addon_connector_equipment_service-12.0.1.1.0.dist-info/top_level.txt
odoo12_addon_connector_equipment_service-12.0.1.1.0.dist-info/RECORD
